dsbuild/.version
dsbuild/__init__.py
dsbuild/__main__.py
dsbuild/version.py
dsbuild-1.1.0.dist-info/METADATA
dsbuild-1.1.0.dist-info/WHEEL
dsbuild-1.1.0.dist-info/entry_points.txt
dsbuild-1.1.0.dist-info/top_level.txt
dsbuild-1.1.0.dist-info/RECORD
