Metadata-Version: 2.4
Name: dsbuild
Version: 1.1.0
Summary: Build infrastructure for python libraries.
Home-page: 
Author: DS
Author-email: grazhopper+pypi@gmail.com
Requires-Dist: wheel
Requires-Dist: setuptools
Requires-Dist: build
Dynamic: author
Dynamic: author-email
Dynamic: requires-dist
Dynamic: summary
